README.txt
setup.py
docs/HISTORY.txt
docs/INSTALL.txt
docs/LICENSE.GPL
docs/LICENSE.txt
my315ok/__init__.py
my315ok/__init__.pyc
my315ok.portlet.rollitems.egg-info/PKG-INFO
my315ok.portlet.rollitems.egg-info/SOURCES.txt
my315ok.portlet.rollitems.egg-info/dependency_links.txt
my315ok.portlet.rollitems.egg-info/entry_points.txt
my315ok.portlet.rollitems.egg-info/namespace_packages.txt
my315ok.portlet.rollitems.egg-info/not-zip-safe
my315ok.portlet.rollitems.egg-info/paster_plugins.txt
my315ok.portlet.rollitems.egg-info/requires.txt
my315ok.portlet.rollitems.egg-info/top_level.txt
my315ok/portlet/__init__.py
my315ok/portlet/__init__.pyc
my315ok/portlet/rollitems/__init__.py
my315ok/portlet/rollitems/__init__.pyc
my315ok/portlet/rollitems/configure.zcml
my315ok/portlet/rollitems/rollportlet.pt
my315ok/portlet/rollitems/rollportlet.py
my315ok/portlet/rollitems/rollportlet.pyc
my315ok/portlet/rollitems/version.txt
my315ok/portlet/rollitems/vocabularies.py
my315ok/portlet/rollitems/vocabularies.pyc
my315ok/portlet/rollitems/browser/__init__.py
my315ok/portlet/rollitems/browser/__init__.pyc
my315ok/portlet/rollitems/browser/configure.zcml
my315ok/portlet/rollitems/browser/images/contents.txt
my315ok/portlet/rollitems/browser/jss/dnmcdocument_javascript.js
my315ok/portlet/rollitems/browser/stylesheets/friendly_link.css
my315ok/portlet/rollitems/locales/my315ok.portlet.rollitems.pot
my315ok/portlet/rollitems/locales/zh/LC_MESSAGES/my315ok.portlet.rollitems.mo
my315ok/portlet/rollitems/locales/zh/LC_MESSAGES/my315ok.portlet.rollitems.po
my315ok/portlet/rollitems/profiles/default/metadata.xml
my315ok/portlet/rollitems/profiles/default/portlets.xml
my315ok/portlet/rollitems/tests/__init__.py
my315ok/portlet/rollitems/tests/base.py
my315ok/portlet/rollitems/tests/test_portlet.py
