Metadata-Version: 1.0
Name: my315ok.portlet.rollitems
Version: 1.0
Summary: a portlet based the collection portlet that provided scroll items
Home-page: http://315ok.org/
Author: adam tang
Author-email: yuejun.tag@gmail.com
License: GPL
Keywords: portlet
Platform: UNKNOWN
Classifier: Framework :: Plone
Classifier: Programming Language :: Python
Classifier: Topic :: Software Development :: Libraries :: Python Modules
